<annotation>
	<folder>collectedimages</folder>
	<filename>Yes.2d1dcf2a-d307-11ee-ac62-4cd577df7666.jpg</filename>
	<path>D:\Sign_language_tool\Tensorflow\workspace\images\collectedimages\Yes.2d1dcf2a-d307-11ee-ac62-4cd577df7666.jpg</path>
	<source>
		<database>Unknown</database>
	</source>
	<size>
		<width>640</width>
		<height>480</height>
		<depth>3</depth>
	</size>
	<segmented>0</segmented>
	<object>
		<name>Yes</name>
		<pose>Unspecified</pose>
		<truncated>0</truncated>
		<difficult>0</difficult>
		<bndbox>
			<xmin>181</xmin>
			<ymin>194</ymin>
			<xmax>402</xmax>
			<ymax>388</ymax>
		</bndbox>
	</object>
</annotation>
